{
    "AbyssalStone": {
        "template": "normal",
        "block": {"name": "Railcraft:cube", "metadata": 6},
        "material": "minecraft:stone",
        "clusterSize": 32,
        "numClusters": 3,
        "meanHeight": 10,
        "maxVariance": 12,
        "retrogen": "true",
        "biomeRestriction": "none",
        "biomes": [],
        "dimensionRestriction": "blacklist",
        "dimensions": [
            1, -1
        ]
    },
    "QuarriedStone": {
        "template": "normal",
        "block": {"name": "Railcraft:cube", "metadata": 7},
        "material": "minecraft:dirt",
        "clusterSize": 24,
        "numClusters": 3,
        "meanHeight": 64,
        "maxVariance": 20,
        "retrogen": "true",
        "biomeRestriction": "none",
        "biomes": [],
        "dimensionRestriction": "whitelist",
        "dimensions": [
            0
        ]
    }
}